stormkey/__init__.py
stormkey/main.py
stormkey-0.1.4.dist-info/LICENSE
stormkey-0.1.4.dist-info/METADATA
stormkey-0.1.4.dist-info/WHEEL
stormkey-0.1.4.dist-info/top_level.txt
stormkey-0.1.4.dist-info/RECORD
