Metadata-Version: 2.1
Name: stormkey
Version: 0.1.4
License-File: LICENSE
